GPTparser/GPTparser.py
GPTparser/__init__.py
GPTparser/extra_scripts/__init__.py
GPTparser/extra_scripts/combinR.py
GPTparser/extra_scripts/j_val.py
GPTparser/extra_scripts/wordcount.py
GPTparser-0.1.0.dist-info/LICENSE
GPTparser-0.1.0.dist-info/METADATA
GPTparser-0.1.0.dist-info/WHEEL
GPTparser-0.1.0.dist-info/entry_points.txt
GPTparser-0.1.0.dist-info/top_level.txt
GPTparser-0.1.0.dist-info/RECORD
