Metadata-Version: 2.1
Name: GPTparser
Version: 0.1.0
Requires-Python: >=3.8
License-File: LICENSE
Requires-Dist: langchain ==0.1.4
Requires-Dist: openai ==1.10.0
Requires-Dist: deeplake
Requires-Dist: tiktoken
Requires-Dist: newspaper3k
Requires-Dist: python-dotenv
